testdatatable/TestDataTable.py
testdatatable/__init__.py
testdatatable-0.2.6.dist-info/LICENSE
testdatatable-0.2.6.dist-info/METADATA
testdatatable-0.2.6.dist-info/WHEEL
testdatatable-0.2.6.dist-info/entry_points.txt
testdatatable-0.2.6.dist-info/top_level.txt
testdatatable-0.2.6.dist-info/RECORD
