Metadata-Version: 2.1
Name: testdatatable
Version: 0.2.6
Summary: TestDataTable
Home-page: https://github.com/damies13/TestDataTable
Author: damies13
Author-email: damies13+TestDataTable@gmail.com
Project-URL: Getting Help, https://github.com/damies13/TestDataTable#getting-help
Project-URL: Say Thanks!, https://github.com/damies13/TestDataTable#donations
Project-URL: Source, https://github.com/damies13/TestDataTable
Classifier: Development Status :: 5 - Production/Stable
Classifier: Topic :: Software Development :: Testing
Classifier: Programming Language :: Python :: 3.7
Classifier: License :: OSI Approved :: GNU General Public License v3 (GPLv3)
Classifier: Operating System :: OS Independent
Requires-Python: >=3.7
License-File: LICENSE
Requires-Dist: configparser
Requires-Dist: HTTPServer
Requires-Dist: sqlite3worker
